{
	"packages": [
		{
			"name": "quirkbot",
			"maintainer": "Quirkbot",
			"websiteURL": "https://github.com/Quirkbot/QuirkbotArduinoHardware",
			"email": "support@quirkbot.com",
			"help": {
				"online": "https://github.com/Quirkbot/QuirkbotArduinoHardware/issues"
			},
			"platforms": [
				{
					"name": "Quirkbot AVR Boards",
					"architecture": "avr",
					"version": "0.0.5#1",
					"category": "Contributed",
					"url": "https://github.com/Quirkbot/QuirkbotArduinoHardware/raw/master/quirkbot-avr.tar.bz2",
					"archiveFileName": "quirkbot-avr.tar.bz2",
					"checksum": "SHA-256:e451742c0462cf32e425e2b901421a636b0469fa53143b2904d439a215ee6b01",
					"size": "217859",
					"help": {
						"online": "https://github.com/Quirkbot/QuirkbotArduinoHardware/issues"
					},
					"boards": [
						{
							"name": "Quirkbot"
						}
					],
					"toolsDependencies": [
						{
							"packager": "arduino",
							"name": "avr-gcc",
							"version": "4.8.1-arduino5"
						},
						{
							"packager": "arduino",
							"name": "avrdude",
							"version": "6.0.1-arduino5"
						}
					]
				}
			],
			"tools": []
		}
	]
}
